Metadata-Version: 2.1
Name: py-codigofacilito
Version: 0.0.1
Summary: CodigoFacilito endpoints
Home-page: https://github.com/eduardogpg/py_codigofacilito_test
Author: Eduardo Ismael García Pérez
Author-email: eduardo78d@gmail.com
License: MIT
Platform: UNKNOWN
Classifier: Development Status :: 3 - Alpha
Classifier: Intended Audience :: Developers
Classifier: Topic :: Software Development :: Build Tools
Classifier: License :: OSI Approved :: MIT License
Classifier: Programming Language :: Python :: 3
